LICENSE.txt
MANIFEST.in
README.md
setup.cfg
setup.py
xri/__init__.py
xri/compat.py
xri.egg-info/PKG-INFO
xri.egg-info/SOURCES.txt
xri.egg-info/dependency_links.txt
xri.egg-info/top_level.txt