Metadata-Version: 2.1
Name: xri
Version: 0.7.1
Summary: Simple and efficient Python data types for URIs and IRIs
Author: Nigel Small
Author-email: technige@nige.tech
License: Apache 2.0
Keywords: URI,IRI,RFC3986,RFC3987,RFC6570
Classifier: Intended Audience :: Developers
Classifier: License :: OSI Approved :: Apache Software License
Classifier: Programming Language :: Python :: 3
Classifier: Topic :: Internet
Classifier: Topic :: Internet :: File Transfer Protocol (FTP)
Classifier: Topic :: Internet :: WWW/HTTP
Classifier: Topic :: Software Development :: Internationalization
Classifier: Topic :: Software Development :: Libraries
Classifier: Topic :: System :: Networking
Classifier: Topic :: Text Processing
Classifier: Topic :: Utilities
Requires-Python: >=3.7
License-File: LICENSE.txt
